gisrep/__init__.py
gisrep/cli.py
gisrep/config.py
gisrep/errors.py
gisrep/gisrep.py
gisrep/templates/__init__.py
gisrep/templates/list_by_labels.html.py
gisrep/templates/list_by_labels.html.tplt
gisrep/templates/simple_report.md.tplt
gisrep/templates/template_manager.py
gisrep-0.2.3.dist-info/DESCRIPTION.rst
gisrep-0.2.3.dist-info/METADATA
gisrep-0.2.3.dist-info/RECORD
gisrep-0.2.3.dist-info/WHEEL
gisrep-0.2.3.dist-info/entry_points.txt
gisrep-0.2.3.dist-info/metadata.json
gisrep-0.2.3.dist-info/top_level.txt
