Metadata-Version: 2.0
Name: gisrep
Version: 0.2.3
Summary: The command line Github issues reporter
Home-page: https://github.com/briggySmalls/gisrep
Author: Sam Briggs
Author-email: briggySmalls90@gmail.com
License: GPLv3
Project-URL: Bug Tracker, https://github.com/briggySmalls/gisrep/issues
Project-URL: Documentation, https://briggysmalls.github.io/gisrep/index.html
Project-URL: Source Code, https://github.com/briggySmalls/gisrep
Keywords: Github issues tracker reports reporting documentation release note publish
Platform: UNKNOWN
Classifier: Intended Audience :: Developers
Classifier: Natural Language :: English
Classifier: License :: OSI Approved :: GNU General Public License v3 or later (GPLv3+)
Classifier: Programming Language :: Python :: 3.4
Classifier: Programming Language :: Python :: 3.5
Classifier: Programming Language :: Python :: 3.6
Classifier: Topic :: Software Development :: Bug Tracking
Classifier: Topic :: Software Development :: Documentation
Requires-Dist: toml
Requires-Dist: jinja2
Requires-Dist: PyGithub
Requires-Dist: keyring (>=10.6)
Requires-Dist: pyperclip
